wagtail_pygments/__init__.py
wagtail_pygments/blocks.py
wagtail_pygments/settings.py
wagtail_pygments-0.1.1.dist-info/LICENSE
wagtail_pygments-0.1.1.dist-info/METADATA
wagtail_pygments-0.1.1.dist-info/WHEEL
wagtail_pygments-0.1.1.dist-info/top_level.txt
wagtail_pygments-0.1.1.dist-info/RECORD
