Metadata-Version: 2.1
Name: wagtail-pygments
Version: 0.1.1
Summary: A block render syntax highlighter for Wagtail CMS.
Home-page: https://github.com/truongvan/wagtail-pygments.git
Author: Truong Van
Author-email: truongvan@live.com
License: BSD-3-Clause
Platform: UNKNOWN
Classifier: Environment :: Web Environment
Classifier: Framework :: Django
Classifier: Framework :: Wagtail
Classifier: Framework :: Wagtail :: 2
Classifier: Intended Audience :: Developers
Classifier: License :: OSI Approved :: BSD License
Classifier: Operating System :: OS Independent
Classifier: Programming Language :: Python :: 3
Classifier: Programming Language :: Python :: 3.8
Classifier: Topic :: Internet :: WWW/HTTP
Classifier: Topic :: Internet :: WWW/HTTP :: Dynamic Content
Requires-Dist: pygments (>=2.6)
Requires-Dist: wagtail (>=2)
